pikapika/__init__.py
pikapika/test.py
pikaqiao-0.0.post2.dist-info/METADATA
pikaqiao-0.0.post2.dist-info/WHEEL
pikaqiao-0.0.post2.dist-info/top_level.txt
pikaqiao-0.0.post2.dist-info/RECORD
